instagram_api1/__init__.py
instagram_api1/rest_instagram.py
instagram_api1/sessionid.py
instagram_api1/utils.py
instagram_api1-0.4.dist-info/LICENSE.txt
instagram_api1-0.4.dist-info/METADATA
instagram_api1-0.4.dist-info/WHEEL
instagram_api1-0.4.dist-info/top_level.txt
instagram_api1-0.4.dist-info/RECORD
