Metadata-Version: 2.1
Name: instagram_api1
Version: 0.4
Summary: مكتبه تخص الانستقرام
Home-page: https://github.com/AL-MHIB
Author: ALMHEB
Author-email: appasqw107@gmail.com
Classifier: Programming Language :: Python :: 3
Classifier: License :: OSI Approved :: MIT License
Classifier: Operating System :: OS Independent
Requires-Python: >=3.6
License-File: LICENSE.txt
Requires-Dist: requests
